pyftrace/__init__.py
pyftrace/main.py
pyftrace/tracer.py
pyftrace/tui.py
pyftrace/utils.py
pyftrace/engine/__init__.py
pyftrace/engine/pyftrace_monitoring.py
pyftrace/engine/pyftrace_setprofile.py
tests/__init__.py
tests/runtests.py
pyftrace-0.3.1.dist-info/LICENSE
pyftrace-0.3.1.dist-info/METADATA
pyftrace-0.3.1.dist-info/WHEEL
pyftrace-0.3.1.dist-info/entry_points.txt
pyftrace-0.3.1.dist-info/top_level.txt
pyftrace-0.3.1.dist-info/RECORD
