Metadata-Version: 2.1
Name: pyftrace
Version: 0.3.1
Summary: Python function tracing tool.
Home-page: https://github.com/kangtegong/pyftrace
Author: Kang Minchul
Author-email: tegongkang@gmail.com
Requires-Python: >=3.8
License-File: LICENSE
Requires-Dist: windows-curses; sys_platform == "win32"
